{
  "$schema": "https://schema.management.azure.com/schemas/2015-01-01/deploymentParameters.json#",
  "contentVersion": "1.0.0.0",
  "parameters": {
    "appName": {
      "value": "duDadApp"
    },
    "skuName": {
      "value": "S1"
    },
    "du22dbmsAdminLogin": {
      "value": "sqladmin"
    },
    "myDBName": {
      "value": "dudb"
    },
    "du22dbmsAdminLoginPassword": {
      "reference": {
        "keyVault": {
          "id": "/subscriptions/b8c7d821-4fbb-4089-8978-b966512a6a45/resourceGroups/rg-shared/providers/Microsoft.KeyVault/vaults/imaKeyvault"
        },
        "secretName": "duPassword"
      }
    },
    "envName": {
      "value": "du22"
    },
    "favoriteColor": {
      "value": "lightpink"
    }
  }
}
